odoo/addons/partner_code_program_sale/README.rst
odoo/addons/partner_code_program_sale/__init__.py
odoo/addons/partner_code_program_sale/__manifest__.py
odoo/addons/partner_code_program_sale/i18n/es.po
odoo/addons/partner_code_program_sale/models/__init__.py
odoo/addons/partner_code_program_sale/models/sale_order.py
odoo/addons/partner_code_program_sale/models/sale_report.py
odoo/addons/partner_code_program_sale/readme/CONFIGURE.md
odoo/addons/partner_code_program_sale/readme/CONTRIBUTORS.md
odoo/addons/partner_code_program_sale/readme/DESCRIPTION.md
odoo/addons/partner_code_program_sale/readme/INSTALL.md
odoo/addons/partner_code_program_sale/readme/USAGE.md
odoo/addons/partner_code_program_sale/static/description/icon.png
odoo/addons/partner_code_program_sale/static/description/index.html
odoo/addons/partner_code_program_sale/tests/__init__.py
odoo/addons/partner_code_program_sale/tests/test_partner_code_program_sale.py
odoo/addons/partner_code_program_sale/views/sale_order.xml
odoo/addons/partner_code_program_sale/views/sale_report.xml
odoo_addon_partner_code_program_sale-18.0.1.0.0.1.dist-info/METADATA
odoo_addon_partner_code_program_sale-18.0.1.0.0.1.dist-info/WHEEL
odoo_addon_partner_code_program_sale-18.0.1.0.0.1.dist-info/top_level.txt
odoo_addon_partner_code_program_sale-18.0.1.0.0.1.dist-info/RECORD
