Metadata-Version: 2.1
Name: odoo-addon-partner_code_program_sale
Version: 18.0.1.0.0.1
Requires-Python: >=3.10
Requires-Dist: odoo-addon-partner_code_program==18.0.*
Requires-Dist: odoo==18.0.*
Summary: Adds the partner code program fields on sales
Home-page: https://github.com/sygel-technology/sy-partner-contact
License: AGPL-3
Author: Sygel
Classifier: Programming Language :: Python
Classifier: Framework :: Odoo
Classifier: Framework :: Odoo :: 18.0
Classifier: License :: OSI Approved :: GNU Affero General Public License v3
